[
  {
    "word": "chien",
    "correct": "собака",
    "options": [
      "кошка",
      "лошадь",
      "собака",
      "птица"
    ],
    "level": "A1"
  },
  {
    "word": "maison",
    "correct": "дом",
    "options": [
      "окно",
      "дверь",
      "дом",
      "крыша"
    ],
    "level": "A1"
  },
  {
    "word": "livre",
    "correct": "книга",
    "options": [
      "тетрадь",
      "книга",
      "ручка",
      "письмо"
    ],
    "level": "A1"
  },
  {
    "word": "soleil",
    "correct": "солнце",
    "options": [
      "луна",
      "солнце",
      "звезда",
      "небо"
    ],
    "level": "A1"
  },
  {
    "word": "voiture",
    "correct": "машина",
    "options": [
      "велосипед",
      "поезд",
      "самолёт",
      "машина"
    ],
    "level": "A1"
  }
]